routelit_flask/__init__.py
routelit_flask/adapter.py
routelit_flask/json_encoder.py
routelit_flask/request.py
routelit_flask/utils.py
routelit_flask-0.5.0.dist-info/METADATA
routelit_flask-0.5.0.dist-info/WHEEL
routelit_flask-0.5.0.dist-info/licenses/LICENSE
routelit_flask-0.5.0.dist-info/RECORD
