Metadata-Version: 2.4
Name: routelit-flask
Version: 0.5.0
Summary: A Flask adapter for the RouteLit framework, enabling seamless integration of RouteLit's reactive UI components with Flask web applications
Project-URL: Homepage, https://routelit.github.io/routelit-flask/
Project-URL: Repository, https://github.com/routelit/routelit-flask
Project-URL: Documentation, https://routelit.github.io/routelit-flask/
Author-email: Rolando Gómez Tabar <rolangom@gmail.com>
License: Apache-2.0
License-File: LICENSE
Keywords: python
Classifier: Intended Audience :: Developers
Classifier: Programming Language :: Python
Classifier: Programming Language :: Python :: 3
Classifier: Programming Language :: Python :: 3.9
Classifier: Programming Language :: Python :: 3.10
Classifier: Programming Language :: Python :: 3.11
Classifier: Programming Language :: Python :: 3.12
Classifier: Programming Language :: Python :: 3.13
Classifier: Topic :: Software Development :: Libraries :: Python Modules
Requires-Python: <4.0,>=3.9
Requires-Dist: flask>=2.0.0
Requires-Dist: jinja2>=3.0.0
Requires-Dist: routelit>=0.5.8
